twosigma/memento/__about__.py
twosigma/memento/__init__.py
twosigma/memento/base.py
twosigma/memento/call_stack.py
twosigma/memento/code_hash.py
twosigma/memento/configuration.py
twosigma/memento/context.py
twosigma/memento/dependency_graph.py
twosigma/memento/exception.py
twosigma/memento/external.py
twosigma/memento/logging.py
twosigma/memento/memento.py
twosigma/memento/metadata.py
twosigma/memento/partition.py
twosigma/memento/reference.py
twosigma/memento/resource.py
twosigma/memento/resource_function.py
twosigma/memento/result.py
twosigma/memento/runner.py
twosigma/memento/runner_local.py
twosigma/memento/runner_null.py
twosigma/memento/runner_test.py
twosigma/memento/serialization.py
twosigma/memento/storage.py
twosigma/memento/storage_base.py
twosigma/memento/storage_filesystem.py
twosigma/memento/storage_memory.py
twosigma/memento/storage_null.py
twosigma/memento/types.py
twosigma_memento-0.28.1.dist-info/METADATA
twosigma_memento-0.28.1.dist-info/WHEEL
twosigma_memento-0.28.1.dist-info/licenses/LICENSE.txt
twosigma_memento-0.28.1.dist-info/RECORD
