Metadata-Version: 2.1
Name: twosigma_memento
Version: 0.28.1
Summary: Two Sigma Memento Core
Project-URL: Documentation, https://github.com/twosigma/memento#readme
Project-URL: Issues, https://github.com/twosigma/memento/issues
Project-URL: Source, https://github.com/twosigma/memento
Author-email: Mark Roth <mark.roth@twosigma.com>
License-Expression: Apache-2.0
License-File: LICENSE.txt
Classifier: Development Status :: 4 - Beta
Classifier: Programming Language :: Python
Classifier: Programming Language :: Python :: 3.8
Classifier: Programming Language :: Python :: 3.9
Classifier: Programming Language :: Python :: 3.10
Classifier: Programming Language :: Python :: 3.11
Classifier: Programming Language :: Python :: Implementation :: CPython
Classifier: Programming Language :: Python :: Implementation :: PyPy
Requires-Python: >=3.8
Requires-Dist: graphviz>=0.13
Requires-Dist: jinja2>=3.1.3
Requires-Dist: numpy>=1.15.4
Requires-Dist: pandas>=1.0.5
Requires-Dist: python-dateutil>=2.8
Requires-Dist: pytz>=2020.1
Requires-Dist: pyyaml>=3.13
Requires-Dist: tqdm>=4.31.1
